CHANGES
CONTRIBUTORS.rst
LICENSE
MANIFEST.in
README.rst
setup.cfg
setup.py
examples/async_client.py
examples/code39.py
examples/echo_services.py
examples/eu_vat_service.py
examples/http_basic_auth.py
examples/km_to_miles.py
examples/soap_server.py
examples/trafficvance_apikey.py
src/zeep/__init__.py
src/zeep/__main__.py
src/zeep/cache.py
src/zeep/client.py
src/zeep/exceptions.py
src/zeep/helpers.py
src/zeep/loader.py
src/zeep/ns.py
src/zeep/plugins.py
src/zeep/proxy.py
src/zeep/settings.py
src/zeep/transports.py
src/zeep/utils.py
src/zeep/wsa.py
src/zeep/asyncio/__init__.py
src/zeep/asyncio/bindings.py
src/zeep/asyncio/transport.py
src/zeep/tornado/__init__.py
src/zeep/tornado/bindings.py
src/zeep/tornado/transport.py
src/zeep/wsdl/__init__.py
src/zeep/wsdl/attachments.py
src/zeep/wsdl/definitions.py
src/zeep/wsdl/parse.py
src/zeep/wsdl/utils.py
src/zeep/wsdl/wsdl.py
src/zeep/wsdl/bindings/__init__.py
src/zeep/wsdl/bindings/http.py
src/zeep/wsdl/bindings/soap.py
src/zeep/wsdl/messages/__init__.py
src/zeep/wsdl/messages/base.py
src/zeep/wsdl/messages/http.py
src/zeep/wsdl/messages/mime.py
src/zeep/wsdl/messages/multiref.py
src/zeep/wsdl/messages/soap.py
src/zeep/wsdl/messages/xop.py
src/zeep/wsse/__init__.py
src/zeep/wsse/compose.py
src/zeep/wsse/signature.py
src/zeep/wsse/username.py
src/zeep/wsse/utils.py
src/zeep/xsd/__init__.py
src/zeep/xsd/const.py
src/zeep/xsd/context.py
src/zeep/xsd/printer.py
src/zeep/xsd/schema.py
src/zeep/xsd/utils.py
src/zeep/xsd/valueobjects.py
src/zeep/xsd/visitor.py
src/zeep/xsd/elements/__init__.py
src/zeep/xsd/elements/any.py
src/zeep/xsd/elements/attribute.py
src/zeep/xsd/elements/base.py
src/zeep/xsd/elements/builtins.py
src/zeep/xsd/elements/element.py
src/zeep/xsd/elements/indicators.py
src/zeep/xsd/elements/references.py
src/zeep/xsd/types/__init__.py
src/zeep/xsd/types/any.py
src/zeep/xsd/types/base.py
src/zeep/xsd/types/builtins.py
src/zeep/xsd/types/collection.py
src/zeep/xsd/types/complex.py
src/zeep/xsd/types/simple.py
src/zeep_roboticia.egg-info/PKG-INFO
src/zeep_roboticia.egg-info/SOURCES.txt
src/zeep_roboticia.egg-info/dependency_links.txt
src/zeep_roboticia.egg-info/not-zip-safe
src/zeep_roboticia.egg-info/requires.txt
src/zeep_roboticia.egg-info/top_level.txt
