Metadata-Version: 2.1
Name: zeep-roboticia
Version: 3.4.0
Summary: A modern/fast Python SOAP client based on lxml / requests
Home-page: https://github.com/jjehl/python-zeep
Author: Michael van Tellingen
Author-email: michaelvantellingen@gmail.com
License: MIT
Platform: UNKNOWN
Classifier: Development Status :: 5 - Production/Stable
Classifier: License :: OSI Approved :: MIT License
Classifier: Programming Language :: Python :: 2
Classifier: Programming Language :: Python :: 2.7
Classifier: Programming Language :: Python :: 3
Classifier: Programming Language :: Python :: 3.5
Classifier: Programming Language :: Python :: 3.6
Classifier: Programming Language :: Python :: 3.7
Classifier: Programming Language :: Python :: Implementation :: CPython
Classifier: Programming Language :: Python :: Implementation :: PyPy
Provides-Extra: docs
Provides-Extra: test
Provides-Extra: async
Provides-Extra: tornado
Provides-Extra: xmlsec
